{"sections":{"1632438205dcd4c52e":{"type":"image-with-text","settings":{"text-color":"auto","background-color":"none","container-width":6,"spacing-above":false,"spacing-below":true,"image-height":3,"darken-image":false,"parallax-enabled":false,"text-position":"center","text-width":"medium","overlap":false,"box-around-text":true,"mobile-overlay":true,"image":"shopify:\/\/shop_images\/F10107B2-A394-4DCF-85C3-82A80235ABCD.jpg","overline":"La Bella Vita","title":"Inizia a vivere lo stile di vita Italiano","description":"<p>L'eccellenza è qui vicina a te<\/p>","link-url":"https:\/\/boldriniselleria.com\/pages\/stile-di-vita-italiano#template--15988538900694__163243822008cc1cdd","link-text":"SCOPRI ORA"}},"main":{"type":"page","disabled":true,"settings":{"show-title":false,"background-color":"none","light-text":false,"container-width":3,"spacing-above":false,"spacing-below":true}},"1650232890b4953872":{"type":"featured-text","settings":{"background-color":"none","light-text":false,"container-width":4,"spacing-above":false,"spacing-below":false,"overline":"Un viaggio di emozioni","heading":"Inizia dall'Italia","text":"<p>Il nostro viaggio inizia da qui:<strong> La costiera Amalfitana.<br\/><\/strong>Conosciuta in tutto il mondo come la patria della <strong>\"Dolce Vita\" <\/strong>ci ha ispirato nella creazione della nuova collezione Estate 2022.<\/p><p><strong>Paesaggi mozzafiato<\/strong>, <strong>colori vibranti e sapori unici <\/strong>hanno deliziato la nostra visita sulla famosa costiera.<\/p><p> <\/p>"}},"163243822008cc1cdd":{"type":"grid-with-overlay","blocks":{"163243822008cc1cdd-1":{"type":"image","settings":{"image":"shopify:\/\/shop_images\/7CCD7A66-FAD1-44F8-AF6F-41D59B339E37_98032432-51f8-495f-b2e3-1f96a3788e07.png","wide":true,"tall":false,"retain-ratio":false,"title":"","link-url":"","link-text":""}},"163243822008cc1cdd-3":{"type":"image","settings":{"image":"shopify:\/\/shop_images\/Senza_titolo_1080_x_720_px_1.png","wide":false,"tall":true,"retain-ratio":false,"title":"","link-url":"","link-text":""}},"163243822008cc1cdd-2":{"type":"image","settings":{"image":"shopify:\/\/shop_images\/504EDFB0-3CC9-4407-9296-ABAF6640297A.jpg","wide":false,"tall":false,"retain-ratio":false,"title":"","link-url":"","link-text":""}},"dd134221-c067-4343-8329-87a55375741b":{"type":"image","settings":{"image":"shopify:\/\/shop_images\/IMG_5203.jpg","wide":false,"tall":false,"retain-ratio":false,"title":"","link-url":"","link-text":""}}},"block_order":["163243822008cc1cdd-1","163243822008cc1cdd-3","163243822008cc1cdd-2","dd134221-c067-4343-8329-87a55375741b"],"settings":{"text-style":"light-with-overlay","background-color":"none","spacing":true,"mobile-overlay":true,"container-width":4,"spacing-above":false,"spacing-below":true,"width":3,"mobile-width":"2","heading":"","subtitle":"","link-url":"","link-text":""}},"16502328975b2b4136":{"type":"featured-collection","settings":{"collection":"amalfi","background-color":"none","spacing-above":true,"spacing-below":true,"featured-collection--image--show":false,"featured-collection--description--show":false,"display-type":"grid","products-per-row--desktop":"3","products-per-row--mobile":"2"}},"1650234148239589df":{"type":"featured-text","settings":{"background-color":"none","light-text":false,"container-width":4,"spacing-above":true,"spacing-below":true,"overline":"Il viaggio continua...","heading":"Verso la meravigliosa Toscana","text":"<p>Lasciati accompagnare nella nostra terra di produzione.<br\/>Ogni materiale che utilizziamo proviene dalla toscana, la terra madre delle <strong>eccellenze<\/strong> in verra pelle.<\/p><p>Anche la lavorazione dei nostri prodotti è interamente <strong>MADE IN TOSCANA.<\/strong><\/p>"}},"16502344175a3ae57c":{"type":"grid-with-overlay","blocks":{"16502344165939b0ef-0":{"type":"image","settings":{"image":"shopify:\/\/shop_images\/A719686D-C984-4B35-88FD-91F50B445476.png","wide":true,"tall":true,"retain-ratio":false,"title":"Iniziamo il percorso dalla artistica Lucca","link-url":"","link-text":""}},"16502344165939b0ef-1":{"type":"image","settings":{"image":"shopify:\/\/shop_images\/boldrini_selleria_144395536_738213350446142_3245201487441874349_n.jpg","wide":true,"tall":false,"retain-ratio":false,"title":"","link-url":"","link-text":""}},"16502344165939b0ef-2":{"type":"image","settings":{"image":"shopify:\/\/shop_images\/boldrini_selleria_130566952_698420960687973_5156180651691513149_n.jpg","wide":false,"tall":false,"retain-ratio":false,"title":"","link-url":"","link-text":""}},"16502344165939b0ef-3":{"type":"image","settings":{"image":"shopify:\/\/shop_images\/boldrini_selleria_166065637_926837008145756_4226221200661883493_n.jpg","wide":false,"tall":false,"retain-ratio":false,"title":"","link-url":"","link-text":""}}},"block_order":["16502344165939b0ef-0","16502344165939b0ef-1","16502344165939b0ef-2","16502344165939b0ef-3"],"settings":{"text-style":"box","background-color":"none","spacing":true,"mobile-overlay":true,"container-width":4,"spacing-above":true,"spacing-below":true,"width":4,"mobile-width":"2","heading":"","subtitle":"","link-url":"","link-text":""}},"1650235410b74f9092":{"type":"custom-content","settings":{"custom_html":"<style>\n    {\n        box-sizing: border-box;\n    }\n    \/* Set additional styling options for the columns*\/\n    .column {\n    float: left;\n    width: 50%;\n    }\n\n    .row:after {\n    content: \"\";\n    display: table;\n    clear: both;\n    }\n\n    <\/style>\n \n \n    <div class=\"row\">\n        <div class=\"column\">\n            <video width=\"100%\" controls=\"\">\n  <source src=\"https:\/\/media.giphy.com\/media\/I2dI5OseBohp3ulKbz\/giphy.mp4\" type=\"video\/mp4\">\n<\/source><\/video>\n        <\/div>\n        <div class=\"column\">\n      \n           <p style=\"margin-left:20px;\"><br><br> <br> Andando fino alla meravigliosa Firenze...<\/p>\n        <\/div>\n    <\/div>"}},"165023564505f47fbd":{"type":"featured-collection","settings":{"collection":"toscana","background-color":"none","spacing-above":true,"spacing-below":true,"featured-collection--image--show":false,"featured-collection--description--show":false,"display-type":"grid","products-per-row--desktop":"3","products-per-row--mobile":"1"}}},"order":["1632438205dcd4c52e","main","1650232890b4953872","163243822008cc1cdd","16502328975b2b4136","1650234148239589df","16502344175a3ae57c","1650235410b74f9092","165023564505f47fbd"]}